{
  "timestamp": "2025-09-20T16:13:56.293Z",
  "summary": {
    "passed": 10,
    "failed": 0,
    "warnings": 0,
    "total": 10
  },
  "details": [
    {
      "name": "Vercel Debug Log Function",
      "status": "PASS",
      "details": "Function exists with correct implementation",
      "timestamp": "2025-09-20T16:13:56.290Z"
    },
    {
      "name": "Vercel Logging Environment",
      "status": "PASS",
      "details": "Multiple console methods tested",
      "timestamp": "2025-09-20T16:13:56.291Z"
    },
    {
      "name": "Debug Log Placement",
      "status": "PASS",
      "details": "Extensive logging (70 statements) should provide detailed Vercel logs",
      "timestamp": "2025-09-20T16:13:56.291Z"
    },
    {
      "name": "Apply Error Detection",
      "status": "PASS",
      "details": "Specific \"apply\" error detection implemented",
      "timestamp": "2025-09-20T16:13:56.292Z"
    },
    {
      "name": "Enhanced Error Handler",
      "status": "PASS",
      "details": "Custom error handler with debugging implemented",
      "timestamp": "2025-09-20T16:13:56.292Z"
    },
    {
      "name": "Error Stack Logging",
      "status": "PASS",
      "details": "Error stack traces will be logged",
      "timestamp": "2025-09-20T16:13:56.292Z"
    },
    {
      "name": "Router Wrapping",
      "status": "PASS",
      "details": "Express router wrapped to catch undefined handlers",
      "timestamp": "2025-09-20T16:13:56.292Z"
    },
    {
      "name": "Middleware Wrapping",
      "status": "PASS",
      "details": "Middleware registration wrapped for debugging",
      "timestamp": "2025-09-20T16:13:56.292Z"
    },
    {
      "name": "Route Method Wrapping",
      "status": "PASS",
      "details": "Route method registration wrapped for debugging",
      "timestamp": "2025-09-20T16:13:56.292Z"
    },
    {
      "name": "Single Route Patterns",
      "status": "PASS",
      "details": "All routes use single patterns, no array conflicts",
      "timestamp": "2025-09-20T16:13:56.293Z"
    }
  ],
  "verdict": "DEBUGGING_READY"
}